unknowncli
